{
  "slug": "red-hill-market",
  "name": "Red Hill Market",
  "type": "market",
  "place": "red-hill",
  "zone": "red-hill-plateau",
  "coordinates": {
    "lat": -38.3625,
    "lng": 145.055
  },
  "address": "Red Hill Recreation Reserve, 172 Arthurs Seat Rd, Red Hill VIC 3937",
  "website": "https://www.redhillmarket.com.au",
  "priceBand": "$",
  "authority": {
    "awards": [
      "Victoria's Largest Artisan Craft Market"
    ]
  },
  "signature": "Victoria's finest artisan craft market, held the first Saturday of each month — more than 200 stalls of craft, produce, plants and peninsular makers",
  "editorNote": "Red Hill Market is the single monthly event that pulls the whole Peninsula together. Held on the first Saturday of each month from September through May, the market spreads across the Red Hill Recreation Reserve with more than 200 stalls of handmade craft, gourmet produce, plants, artisan food, and the kind of small-run peninsular makers who do not have retail shops anywhere else.\n\nThe market is big, unapologetically so, and the best way to experience it is to commit to the full morning. Arrive by 9am for parking, work through the food stalls first, circle back for the plants and the craft, and leave before the late-morning crush kicks in. Coffee from one of the mobile roasters; a breakfast sandwich from the Balnarring Bakehouse stall; honey from a ridge apiarist; a bunch of ranunculus from the Merricks flower grower.\n\nOne of the Peninsula's essential weekend experiences. Plan a whole weekend around it if you can — the cellar doors are quieter after midday, and the market sets the mood for the rest of the day.",
  "tags": {
    "mood": [
      "family",
      "big-group",
      "slow",
      "garden"
    ],
    "season": [
      "spring",
      "summer",
      "autumn"
    ],
    "audience": [
      "families",
      "group",
      "couples",
      "first-timers"
    ]
  },
  "heroImage": {
    "src": "/images/placeholder-red-hill-market.jpg",
    "alt": "Red Hill Market — Market",
    "credit": "Red Hill Market",
    "license": "venue-media-kit"
  },
  "gallery": [],
  "featuredPartner": false,
  "lastVerified": "2026-04-09",
  "publishedAt": "2026-04-09"
}