{
  "slug": "ten-minutes-by-tractor",
  "name": "Ten Minutes by Tractor",
  "type": "restaurant",
  "place": "red-hill",
  "zone": "red-hill-plateau",
  "coordinates": { "lat": -38.3619, "lng": 145.0543 },
  "address": "1333 Mornington-Flinders Rd, Red Hill VIC 3937",
  "phone": "+61 3 5989 6455",
  "website": "https://www.tenminutesbytractor.com.au",
  "bookingUrl": "https://www.tenminutesbytractor.com.au/reservations",
  "bookingProvider": "direct",
  "priceBand": "$$$$",
  "authority": {
    "hats": 3,
    "awards": ["Good Food Guide Restaurant of the Year 2023", "Wine List of the Year"]
  },
  "signature": "Estate-grown pinot noir alongside a seasonal degustation rooted in the Ridge vineyard",
  "editorNote": "Three hats and the most considered wine program on the Peninsula — Ten Minutes by Tractor earns every accolade with a degustation that feels genuinely rooted in place. The Ridge vineyard slopes outside the window aren't decoration; they're the story. Book the long lunch: you'll want the afternoon.\n\nThe cooking is technically precise without being cold. The team understands restraint — flavours are clear and confident, not overwrought. The charred bread with cultured butter has become a quiet institution.\n\nBook at least six weeks ahead for weekends. Lunch is the move.",
  "tags": {
    "mood": ["long-lunch", "anniversary", "cellar-door"],
    "season": ["spring", "summer", "autumn"],
    "audience": ["couples", "group"]
  },
  "heroImage": {
    "src": "/images/sourced/article-long-lunch-01.webp",
    "alt": "Ten Minutes by Tractor dining room overlooking the Ridge vineyard, Red Hill",
    "credit": "Wikimedia Commons",
    "license": "tmp-wikimedia"
  },
  "gallery": [],
  "featuredPartner": false,
  "lastVerified": "2026-04-01",
  "publishedAt": "2026-04-01"
}
